ats_base/__init__.py
ats_base/base/__init__.py
ats_base/base/entrance.py
ats_base/base/req.py
ats_base/common/__init__.py
ats_base/common/enum.py
ats_base/common/func.py
ats_base/common/resp.py
ats_base/config/__init__.py
ats_base/config/config.ini
ats_base/config/configure.py
ats_base/config/rewrite_config.py
ats_base/log/__init__.py
ats_base/log/logger.py
ats_base/service/__init__.py
ats_base/service/app.py
ats_base/service/build_in.py
ats_base/service/db.py
ats_base/service/em.py
ats_base/service/mm.py
ats_base/service/msg.py
ats_base/service/pdh.py
ats_base/service/pro.py
ats_base/service/udm.py
ats_base-1.3.43.dist-info/LICENSE
ats_base-1.3.43.dist-info/METADATA
ats_base-1.3.43.dist-info/WHEEL
ats_base-1.3.43.dist-info/top_level.txt
ats_base-1.3.43.dist-info/RECORD
