Metadata-Version: 2.1
Name: ats_base
Version: 1.3.43
Summary: Test Script Development Library
Home-page: https://gitee.com/henry9000/ats_base
Author: zhangyue
Author-email: zhangyue@techen.cn
Project-URL: Bug Tracker, https://gitee.com/henry9000/ats_base/issues
Classifier: Programming Language :: Python :: 3
Classifier: License :: OSI Approved :: MIT License
Classifier: Operating System :: OS Independent
Requires-Python: >=3.9
License-File: LICENSE
Requires-Dist: python-dateutil
Requires-Dist: requests
Requires-Dist: colorlog
